ez_port_forward/__init__.py
ez_port_forward/ez_port_forward.py
ez_port_forward-0.2.0.dist-info/METADATA
ez_port_forward-0.2.0.dist-info/WHEEL
ez_port_forward-0.2.0.dist-info/entry_points.txt
ez_port_forward-0.2.0.dist-info/licenses/LICENSE
ez_port_forward-0.2.0.dist-info/RECORD
