Metadata-Version: 2.3
Name: ez_port_forward
Version: 0.2.0
Summary: Create DNAT port forwarding rules from easy-to-read YAML files.
Project-URL: Homepage, https://github.com/rk-exxec/ez_port_forwarding
Project-URL: Issues, https://github.com/rk-exxec/ez_port_forwarding/issues
Author: Raphael Kriegl
License-File: LICENSE
Keywords: nat,port-forwarding,proxmox
Classifier: Development Status :: 4 - Beta
Classifier: License :: OSI Approved :: GNU General Public License v3 or later (GPLv3+)
Classifier: Programming Language :: Python :: 3
Requires-Python: >=3.9
Requires-Dist: pyyaml
